athos/__init__.py
athos/__main__.py
athos/athos.py
athos/log.py
athos/p4_mininet.py
athos-0.1.3.data/data/etc/athos/topology.json
athos-0.1.3.data/data/etc/athos/umbrella.json
athos-0.1.3.dist-info/AUTHORS
athos-0.1.3.dist-info/LICENSE
athos-0.1.3.dist-info/METADATA
athos-0.1.3.dist-info/WHEEL
athos-0.1.3.dist-info/entry_points.txt
athos-0.1.3.dist-info/pbr.json
athos-0.1.3.dist-info/top_level.txt
athos-0.1.3.dist-info/RECORD
